rf_visuals/__init__.py
rf_visuals/__version__.py
rf_visuals/add.py
rf_visuals/py.typed
rf_visuals-0.0.1.dist-info/METADATA
rf_visuals-0.0.1.dist-info/WHEEL
rf_visuals-0.0.1.dist-info/licenses/AUTHORS.md
rf_visuals-0.0.1.dist-info/licenses/LICENSE
rf_visuals-0.0.1.dist-info/RECORD
