Metadata-Version: 2.4
Name: rf-visuals
Version: 0.0.1
Summary: Visualization and post-processing of RF data (e.g., Touchstone files). Get a presentation and report data fast.
Project-URL: Documentation, https://rasmusravn.github.io/rf-visuals/
Project-URL: Source, https://github.com/rasmusravn/rf-visuals
Author-email: rf-visuals <rasmusravna@gmail.com>
License: MIT License
License-File: AUTHORS.md
License-File: LICENSE
Classifier: Programming Language :: Python :: 3
Classifier: Programming Language :: Python :: 3.13
Classifier: Programming Language :: Python :: Implementation :: CPython
Classifier: Programming Language :: Python :: Implementation :: PyPy
Requires-Python: >=3.13
Requires-Dist: coverage>=7.6.9
Requires-Dist: pydantic>=2.10.4
